README.md
setup.py
jefrysaludo/__init__.py
jefrysaludo/saludo.py
jefrysaludo.egg-info/PKG-INFO
jefrysaludo.egg-info/SOURCES.txt
jefrysaludo.egg-info/dependency_links.txt
jefrysaludo.egg-info/top_level.txt