Metadata-Version: 2.1
Name: jefrysaludo
Version: 0.1
Summary: Esta es la descripcion de mi paquete
Home-page: https://github.com/Jefry-bot/jefrysaludo
Author: Jefry Zarate
Author-email: jefryzarate@gmail.com
License: MIT
Download-URL: https://github.com/Jefry-bot/jefrysaludo/tarball/0.1
Keywords: testing,logging,example
Platform: UNKNOWN
